Metadata-Version: 1.1
Name: root-numpy
Version: 4.8.0
Summary: The interface between ROOT and NumPy
Home-page: http://scikit-hep.org/root_numpy
Author: The scikit-hep developers
Author-email: scikit-hep-admins@googlegroups.com
License: new BSD
Platform: UNKNOWN
Classifier: Intended Audience :: Science/Research
Classifier: Intended Audience :: Developers
Classifier: Topic :: Software Development
Classifier: Topic :: Scientific/Engineering
Classifier: Topic :: Utilities
Classifier: Operating System :: POSIX
Classifier: Operating System :: Unix
Classifier: Operating System :: MacOS
Classifier: License :: OSI Approved :: BSD License
Classifier: Programming Language :: Python
Classifier: Programming Language :: Python :: 2
Classifier: Programming Language :: Python :: 2.7
Classifier: Programming Language :: Python :: 3
Classifier: Programming Language :: Python :: 3.6
Classifier: Programming Language :: Python :: 3.7
Classifier: Programming Language :: C++
Classifier: Programming Language :: Cython
Classifier: Development Status :: 5 - Production/Stable
